anyparse/__init__.py
anyparse/anyparse.py
anyparse-0.0.2.dist-info/LICENSE
anyparse-0.0.2.dist-info/METADATA
anyparse-0.0.2.dist-info/WHEEL
anyparse-0.0.2.dist-info/top_level.txt
anyparse-0.0.2.dist-info/RECORD
